{"name": "ind2959", "unsafe_region": [0.10566621749024081, 0.2798720737625679], "archive_sparseness": 3.1372623443603516, "mbr": {"svg": "<svg version=\"1.0\" xmlns=\"http://www.w3.org/2000/svg\" height=\"28\" width=\"28\"><path d=\" M11,25 C9,24 9,24 11,24 C12,24 14,24 15,25 C17,25 17,19.882950319390353 15,25 C13,25 11,25 11,25 Z\" /></svg>", "expected_label": 5, "satisfy_requirements": true, "predicted_label": 5, "prediction_quality": 0.03070719540119171}, "neighbors": [{"svg": "<svg version=\"1.0\" xmlns=\"http://www.w3.org/2000/svg\" height=\"28\" width=\"28\"><path d=\" M11,23.047474314450408 C9,24 9,24 11,24 C12,24 14,24 15,25 C17,25 17,19.882950319390353 15,25 C13,25 11,25 11,25 Z\" /></svg>", "expected_label": 5, "satisfy_requirements": true, "predicted_label": 5, "prediction_quality": 0.03886687755584717}, {"svg": "<svg version=\"1.0\" xmlns=\"http://www.w3.org/2000/svg\" height=\"28\" width=\"28\"><path d=\" M11,25 C9,24 9,24 11,24 C12,24 14,24 15.577718827487631,25 C17,25 17,19.882950319390353 15,25 C13,25 11,25 11,25 Z\" /></svg>", "expected_label": 5, "satisfy_requirements": true, "predicted_label": 5, "prediction_quality": 0.026929527521133423}, {"svg": "<svg version=\"1.0\" xmlns=\"http://www.w3.org/2000/svg\" height=\"28\" width=\"28\"><path d=\" M11,25 C9,24 9,24 11,24 C12,24 14,24 15,25 C17,25 17,19.882950319390353 15,25 C13,25 11,25 11,27.95556695757104 Z\" /></svg>", "expected_label": 5, "satisfy_requirements": true, "predicted_label": 5, "prediction_quality": 0.03190690279006958}, {"svg": "<svg version=\"1.0\" xmlns=\"http://www.w3.org/2000/svg\" height=\"28\" width=\"28\"><path d=\" M11,25 C9,24 9,24 11,24 C12,24 14,24 15,25 C17,25 17,19.882950319390353 16.88107351757668,25 C13,25 11,25 11,25 Z\" /></svg>", "expected_label": 5, "satisfy_requirements": true, "predicted_label": 5, "prediction_quality": 0.03203114867210388}, {"svg": "<svg version=\"1.0\" xmlns=\"http://www.w3.org/2000/svg\" height=\"28\" width=\"28\"><path d=\" M11,25 C9,24 9,24 11,24 C12,24 14,24 15,25 C17,25 17,15.224967224734964 15,25 C13,25 11,25 11,25 Z\" /></svg>", "expected_label": 5, "satisfy_requirements": true, "predicted_label": 5, "prediction_quality": 0.05019935965538025}, {"svg": "<svg version=\"1.0\" xmlns=\"http://www.w3.org/2000/svg\" height=\"28\" width=\"28\"><path d=\" M11,25 C9,24 9,24 11,24 C12,24 14,24 15,25 C17,25 17,19.882950319390353 15,25 C13,26.40417845998975 11,25 11,25 Z\" /></svg>", "expected_label": 5, "satisfy_requirements": true, "predicted_label": 5, "prediction_quality": 0.0390859991312027}, {"svg": "<svg version=\"1.0\" xmlns=\"http://www.w3.org/2000/svg\" height=\"28\" width=\"28\"><path d=\" M11,25 C9,24 9,24 11,24 C12,24 14,24 15,25 C17,25 19.8485903083222,19.882950319390353 15,25 C13,25 11,25 11,25 Z\" /></svg>", "expected_label": 5, "satisfy_requirements": true, "predicted_label": 5, "prediction_quality": 0.027048662304878235}, {"svg": "<svg version=\"1.0\" xmlns=\"http://www.w3.org/2000/svg\" height=\"28\" width=\"28\"><path d=\" M11,25 C9,24 9,24 11,24 C12,24 14,24 15,20.53851629167724 C17,25 17,19.882950319390353 15,25 C13,25 11,25 11,25 Z\" /></svg>", "expected_label": 5, "satisfy_requirements": false, "predicted_label": 3, "prediction_quality": -0.242624893784523}, {"svg": "<svg version=\"1.0\" xmlns=\"http://www.w3.org/2000/svg\" height=\"28\" width=\"28\"><path d=\" M11,24.099828453938517 C9,24 9,24 11,24 C12,24 14,24 15,25 C17,25 17,19.882950319390353 15,25 C13,25 11,25 11,25 Z\" /></svg>", "expected_label": 5, "satisfy_requirements": true, "predicted_label": 5, "prediction_quality": 0.02732248604297638}, {"svg": "<svg version=\"1.0\" xmlns=\"http://www.w3.org/2000/svg\" height=\"28\" width=\"28\"><path d=\" M11,25 C9,24 9,24 11,24 C12,24 14,24 15,25 C17,20.042597812606942 17,19.882950319390353 15,25 C13,25 11,25 11,25 Z\" /></svg>", "expected_label": 5, "satisfy_requirements": true, "predicted_label": 5, "prediction_quality": 0.019768312573432922}, {"svg": "<svg version=\"1.0\" xmlns=\"http://www.w3.org/2000/svg\" height=\"28\" width=\"28\"><path d=\" M11,25 C9,24 9,24 11,24 C12,24 14,20.711394060739497 15,25 C17,25 17,19.882950319390353 15,25 C13,25 11,25 11,25 Z\" /></svg>", "expected_label": 5, "satisfy_requirements": false, "predicted_label": 3, "prediction_quality": -0.05350561439990997}, {"svg": "<svg version=\"1.0\" xmlns=\"http://www.w3.org/2000/svg\" height=\"28\" width=\"28\"><path d=\" M11,25 C9,24 9,24 11,24 C12,24 12.629576265384577,24 15,25 C17,25 17,19.882950319390353 15,25 C13,25 11,25 11,25 Z\" /></svg>", "expected_label": 5, "satisfy_requirements": true, "predicted_label": 5, "prediction_quality": 0.030039474368095398}, {"svg": "<svg version=\"1.0\" xmlns=\"http://www.w3.org/2000/svg\" height=\"28\" width=\"28\"><path d=\" M11,25 C9,24 10.667379125065224,24 11,24 C12,24 14,24 15,25 C17,25 17,19.882950319390353 15,25 C13,25 11,25 11,25 Z\" /></svg>", "expected_label": 5, "satisfy_requirements": true, "predicted_label": 5, "prediction_quality": 0.030780762434005737}, {"svg": "<svg version=\"1.0\" xmlns=\"http://www.w3.org/2000/svg\" height=\"28\" width=\"28\"><path d=\" M11,25 C9,24 9,24 11,24 C12,24 14,24 15.259604662134436,25 C17,25 17,19.882950319390353 15,25 C13,25 11,25 11,25 Z\" /></svg>", "expected_label": 5, "satisfy_requirements": true, "predicted_label": 5, "prediction_quality": 0.028231754899024963}, {"svg": "<svg version=\"1.0\" xmlns=\"http://www.w3.org/2000/svg\" height=\"28\" width=\"28\"><path d=\" M11,25 C9,24 9,24 11,24 C12,24 14,24 15,22.10126698423177 C17,25 17,19.882950319390353 15,25 C13,25 11,25 11,25 Z\" /></svg>", "expected_label": 5, "satisfy_requirements": false, "predicted_label": 3, "prediction_quality": -0.1035463809967041}, {"svg": "<svg version=\"1.0\" xmlns=\"http://www.w3.org/2000/svg\" height=\"28\" width=\"28\"><path d=\" M11,25 C9,24 9,24 11,24 C12,24 14,24 15,25 C17,25 11.599125211947634,19.882950319390353 15,25 C13,25 11,25 11,25 Z\" /></svg>", "expected_label": 5, "satisfy_requirements": true, "predicted_label": 5, "prediction_quality": 0.021387532353401184}, {"svg": "<svg version=\"1.0\" xmlns=\"http://www.w3.org/2000/svg\" height=\"28\" width=\"28\"><path d=\" M11,25 C9,24 9,24 11,24 C12,24 14,24 15,25 C17,25 17,19.882950319390353 20.778155836825313,25 C13,25 11,25 11,25 Z\" /></svg>", "expected_label": 5, "satisfy_requirements": false, "predicted_label": 3, "prediction_quality": -0.15870371460914612}, {"svg": "<svg version=\"1.0\" xmlns=\"http://www.w3.org/2000/svg\" height=\"28\" width=\"28\"><path d=\" M11,25 C9,24 9,24 11,24 C12,24 14,24 15,25 C17,24.561240353978405 17,19.882950319390353 15,25 C13,25 11,25 11,25 Z\" /></svg>", "expected_label": 5, "satisfy_requirements": true, "predicted_label": 5, "prediction_quality": 0.0319925993680954}, {"svg": "<svg version=\"1.0\" xmlns=\"http://www.w3.org/2000/svg\" height=\"28\" width=\"28\"><path d=\" M11,25 C9,24 9,24 11,24 C12.300645670403398,24 14,24 15,25 C17,25 17,19.882950319390353 15,25 C13,25 11,25 11,25 Z\" /></svg>", "expected_label": 5, "satisfy_requirements": true, "predicted_label": 5, "prediction_quality": 0.030452311038970947}, {"svg": "<svg version=\"1.0\" xmlns=\"http://www.w3.org/2000/svg\" height=\"28\" width=\"28\"><path d=\" M11,25 C9,24 9,24 11,24 C12,24 14,24 15,25 C17,25 17,25.446634212510542 15,25 C13,25 11,25 11,25 Z\" /></svg>", "expected_label": 5, "satisfy_requirements": true, "predicted_label": 5, "prediction_quality": 0.02029469609260559}, {"svg": "<svg version=\"1.0\" xmlns=\"http://www.w3.org/2000/svg\" height=\"28\" width=\"28\"><path d=\" M11,25 C9,24 9,24 11,24 C12,24 14,24 15,25 C17,25 17,19.882950319390353 9.741112715152314,25 C13,25 11,25 11,25 Z\" /></svg>", "expected_label": 5, "satisfy_requirements": false, "predicted_label": 3, "prediction_quality": -0.035372957587242126}, {"svg": "<svg version=\"1.0\" xmlns=\"http://www.w3.org/2000/svg\" height=\"28\" width=\"28\"><path d=\" M11,25 C9,24 9,24 10.856737165851824,24 C12,24 14,24 15,25 C17,25 17,19.882950319390353 15,25 C13,25 11,25 11,25 Z\" /></svg>", "expected_label": 5, "satisfy_requirements": true, "predicted_label": 5, "prediction_quality": 0.03088061511516571}, {"svg": "<svg version=\"1.0\" xmlns=\"http://www.w3.org/2000/svg\" height=\"28\" width=\"28\"><path d=\" M11,25 C9,24 9,24 11,24 C12,27.047352731180865 14,24 15,25 C17,25 17,19.882950319390353 15,25 C13,25 11,25 11,25 Z\" /></svg>", "expected_label": 5, "satisfy_requirements": true, "predicted_label": 5, "prediction_quality": 0.012029118835926056}, {"svg": "<svg version=\"1.0\" xmlns=\"http://www.w3.org/2000/svg\" height=\"28\" width=\"28\"><path d=\" M11,25 C9,24 9,24 11,24 C12,24 14,24 15,25 C17,25 17,19.882950319390353 17.00818692840308,25 C13,25 11,25 11,25 Z\" /></svg>", "expected_label": 5, "satisfy_requirements": true, "predicted_label": 5, "prediction_quality": 0.032621294260025024}, {"svg": "<svg version=\"1.0\" xmlns=\"http://www.w3.org/2000/svg\" height=\"28\" width=\"28\"><path d=\" M11,25 C9,24 9,24 11,24 C12,24 14,24 15,25 C17,25 17,19.882950319390353 15,25 C13,25 11,21.943482827824237 11,25 Z\" /></svg>", "expected_label": 5, "satisfy_requirements": true, "predicted_label": 5, "prediction_quality": 0.01176346093416214}, {"svg": "<svg version=\"1.0\" xmlns=\"http://www.w3.org/2000/svg\" height=\"28\" width=\"28\"><path d=\" M11,25 C9,24 9,24 11,24 C12,24 14,24 15,25 C17,25 17,17.612442161895085 15,25 C13,25 11,25 11,25 Z\" /></svg>", "expected_label": 5, "satisfy_requirements": true, "predicted_label": 5, "prediction_quality": 0.046040549874305725}, {"svg": "<svg version=\"1.0\" xmlns=\"http://www.w3.org/2000/svg\" height=\"28\" width=\"28\"><path d=\" M11,25 C9,24 9,24 11,24 C12,24 14,24 15,25 C17,25 17,19.882950319390353 15,24.785625757287384 C13,25 11,25 11,25 Z\" /></svg>", "expected_label": 5, "satisfy_requirements": true, "predicted_label": 5, "prediction_quality": 0.0332568883895874}, {"svg": "<svg version=\"1.0\" xmlns=\"http://www.w3.org/2000/svg\" height=\"28\" width=\"28\"><path d=\" M11,25 C9,24 9,24 11,24 C12,24 8.147605064826264,24 15,25 C17,25 17,19.882950319390353 15,25 C13,25 11,25 11,25 Z\" /></svg>", "expected_label": 5, "satisfy_requirements": true, "predicted_label": 5, "prediction_quality": 0.021188415586948395}, {"svg": "<svg version=\"1.0\" xmlns=\"http://www.w3.org/2000/svg\" height=\"28\" width=\"28\"><path d=\" M11,25 C9,24 9,24 11,24 C12,24 14,24 15,27.890447927162505 C17,25 17,19.882950319390353 15,25 C13,25 11,25 11,25 Z\" /></svg>", "expected_label": 5, "satisfy_requirements": true, "predicted_label": 5, "prediction_quality": 0.04336473345756531}, {"svg": "<svg version=\"1.0\" xmlns=\"http://www.w3.org/2000/svg\" height=\"28\" width=\"28\"><path d=\" M11,25 C9,24 9,24 11,24 C12,24 14,24 15,25 C17,25 20.381863843086823,19.882950319390353 15,25 C13,25 11,25 11,25 Z\" /></svg>", "expected_label": 5, "satisfy_requirements": true, "predicted_label": 5, "prediction_quality": 0.027010798454284668}, {"svg": "<svg version=\"1.0\" xmlns=\"http://www.w3.org/2000/svg\" height=\"28\" width=\"28\"><path d=\" M11,25 C9,24 5.485651649504748,24 11,24 C12,24 14,24 15,25 C17,25 17,19.882950319390353 15,25 C13,25 11,25 11,25 Z\" /></svg>", "expected_label": 5, "satisfy_requirements": true, "predicted_label": 5, "prediction_quality": 0.030537933111190796}, {"svg": "<svg version=\"1.0\" xmlns=\"http://www.w3.org/2000/svg\" height=\"28\" width=\"28\"><path d=\" M11,25 C9,24 9,24 11,24 C12,24 14,24 15,25 C17,25 17,19.882950319390353 14.48713064187675,25 C13,25 11,25 11,25 Z\" /></svg>", "expected_label": 5, "satisfy_requirements": true, "predicted_label": 5, "prediction_quality": 0.02998906373977661}, {"svg": "<svg version=\"1.0\" xmlns=\"http://www.w3.org/2000/svg\" height=\"28\" width=\"28\"><path d=\" M11,20.13886995003495 C9,24 9,24 11,24 C12,24 14,24 15,25 C17,25 17,19.882950319390353 15,25 C13,25 11,25 11,25 Z\" /></svg>", "expected_label": 5, "satisfy_requirements": true, "predicted_label": 5, "prediction_quality": 0.09312133491039276}, {"svg": "<svg version=\"1.0\" xmlns=\"http://www.w3.org/2000/svg\" height=\"28\" width=\"28\"><path d=\" M11,25 C9,24 9,24 11,24 C6.921756975243333,24 14,24 15,25 C17,25 17,19.882950319390353 15,25 C13,25 11,25 11,25 Z\" /></svg>", "expected_label": 5, "satisfy_requirements": true, "predicted_label": 5, "prediction_quality": 0.025052964687347412}, {"svg": "<svg version=\"1.0\" xmlns=\"http://www.w3.org/2000/svg\" height=\"28\" width=\"28\"><path d=\" M11,25 C9,24 9,24 11,24 C12,24 14,24 15,25 C17,25 17,19.882950319390353 15,25 C13,25 11,25 11,20.554545220177797 Z\" /></svg>", "expected_label": 5, "satisfy_requirements": true, "predicted_label": 5, "prediction_quality": 0.019763588905334473}, {"svg": "<svg version=\"1.0\" xmlns=\"http://www.w3.org/2000/svg\" height=\"28\" width=\"28\"><path d=\" M11,25 C9,24 9,24 11,24 C12,24 14,24 15,27.937290278661465 C17,25 17,19.882950319390353 15,25 C13,25 11,25 11,25 Z\" /></svg>", "expected_label": 5, "satisfy_requirements": true, "predicted_label": 5, "prediction_quality": 0.04287995398044586}, {"svg": "<svg version=\"1.0\" xmlns=\"http://www.w3.org/2000/svg\" height=\"28\" width=\"28\"><path d=\" M11,25 C9,24 9,24 11,24 C12,24 14,24 15,25 C17,25 17,19.882950319390353 15,23.488559304466364 C13,25 11,25 11,25 Z\" /></svg>", "expected_label": 5, "satisfy_requirements": true, "predicted_label": 5, "prediction_quality": 0.023772582411766052}, {"svg": "<svg version=\"1.0\" xmlns=\"http://www.w3.org/2000/svg\" height=\"28\" width=\"28\"><path d=\" M11,25 C9,24 9,24 11,24 C12,24 11.179427267901854,24 15,25 C17,25 17,19.882950319390353 15,25 C13,25 11,25 11,25 Z\" /></svg>", "expected_label": 5, "satisfy_requirements": true, "predicted_label": 5, "prediction_quality": 0.027131393551826477}, {"svg": "<svg version=\"1.0\" xmlns=\"http://www.w3.org/2000/svg\" height=\"28\" width=\"28\"><path d=\" M11,25 C9,24 9,24 11,24 C12,24 14,24 15,25 C17,25 17,19.882950319390353 15,25 C13,25 11,25 11,25.523801182002543 Z\" /></svg>", "expected_label": 5, "satisfy_requirements": true, "predicted_label": 5, "prediction_quality": 0.03094172477722168}, {"svg": "<svg version=\"1.0\" xmlns=\"http://www.w3.org/2000/svg\" height=\"28\" width=\"28\"><path d=\" M11,25 C9,22.49886479121514 9,24 11,24 C12,24 14,24 15,25 C17,25 17,19.882950319390353 15,25 C13,25 11,25 11,25 Z\" /></svg>", "expected_label": 5, "satisfy_requirements": true, "predicted_label": 5, "prediction_quality": 0.02998127043247223}, {"svg": "<svg version=\"1.0\" xmlns=\"http://www.w3.org/2000/svg\" height=\"28\" width=\"28\"><path d=\" M11,25 C9,24 9,24 11,24 C12,24 14,24 15,25 C17,25 17,19.882950319390353 15,25 C13,23.295903930057445 11,25 11,25 Z\" /></svg>", "expected_label": 5, "satisfy_requirements": true, "predicted_label": 5, "prediction_quality": 0.018321514129638672}, {"svg": "<svg version=\"1.0\" xmlns=\"http://www.w3.org/2000/svg\" height=\"28\" width=\"28\"><path d=\" M11,25 C9,24 9,24 11,24 C12,25.278931540971826 14,24 15,25 C17,25 17,19.882950319390353 15,25 C13,25 11,25 11,25 Z\" /></svg>", "expected_label": 5, "satisfy_requirements": true, "predicted_label": 5, "prediction_quality": 0.019869625568389893}, {"svg": "<svg version=\"1.0\" xmlns=\"http://www.w3.org/2000/svg\" height=\"28\" width=\"28\"><path d=\" M11,25 C9,24 9,24 11,24 C12,24 14,24 15,25 C17,25 17,19.882950319390353 12.843448061698325,25 C13,25 11,25 11,25 Z\" /></svg>", "expected_label": 5, "satisfy_requirements": false, "predicted_label": 3, "prediction_quality": -0.008432745933532715}, {"svg": "<svg version=\"1.0\" xmlns=\"http://www.w3.org/2000/svg\" height=\"28\" width=\"28\"><path d=\" M11,25 C9,24 9,24 11,24 C12,24 14,24 10.288022762813188,25 C17,25 17,19.882950319390353 15,25 C13,25 11,25 11,25 Z\" /></svg>", "expected_label": 5, "satisfy_requirements": true, "predicted_label": 5, "prediction_quality": 0.01260143518447876}, {"svg": "<svg version=\"1.0\" xmlns=\"http://www.w3.org/2000/svg\" height=\"28\" width=\"28\"><path d=\" M11,25 C9,24 9,24 11,24 C12,24 14,24 15,25 C17,25 17,19.882950319390353 10.008983854398188,25 C13,25 11,25 11,25 Z\" /></svg>", "expected_label": 5, "satisfy_requirements": false, "predicted_label": 3, "prediction_quality": -0.033087655901908875}, {"svg": "<svg version=\"1.0\" xmlns=\"http://www.w3.org/2000/svg\" height=\"28\" width=\"28\"><path d=\" M11,25 C9,24 9,24 11,24 C9.710838551184395,24 14,24 15,25 C17,25 17,19.882950319390353 15,25 C13,25 11,25 11,25 Z\" /></svg>", "expected_label": 5, "satisfy_requirements": true, "predicted_label": 5, "prediction_quality": 0.029131561517715454}, {"svg": "<svg version=\"1.0\" xmlns=\"http://www.w3.org/2000/svg\" height=\"28\" width=\"28\"><path d=\" M11,25 C9,24 9,27.341045296705932 11,24 C12,24 14,24 15,25 C17,25 17,19.882950319390353 15,25 C13,25 11,25 11,25 Z\" /></svg>", "expected_label": 5, "satisfy_requirements": true, "predicted_label": 5, "prediction_quality": 0.02883508801460266}, {"svg": "<svg version=\"1.0\" xmlns=\"http://www.w3.org/2000/svg\" height=\"28\" width=\"28\"><path d=\" M11,25 C9,24 9,24 11,24 C12,24 14,24 15,25 C17,25 17,19.882950319390353 10.455186543977305,25 C13,25 11,25 11,25 Z\" /></svg>", "expected_label": 5, "satisfy_requirements": false, "predicted_label": 3, "prediction_quality": -0.0320461243391037}, {"svg": "<svg version=\"1.0\" xmlns=\"http://www.w3.org/2000/svg\" height=\"28\" width=\"28\"><path d=\" M11,25 C9,24 9,24 11,24 C12,24 14,24 15,25 C17,25 17,19.882950319390353 11.343936216949029,25 C13,25 11,25 11,25 Z\" /></svg>", "expected_label": 5, "satisfy_requirements": false, "predicted_label": 3, "prediction_quality": -0.03757032752037048}, {"svg": "<svg version=\"1.0\" xmlns=\"http://www.w3.org/2000/svg\" height=\"28\" width=\"28\"><path d=\" M11,25 C9,24 9,24 11,24 C12,24 14,24 16.52909908332056,25 C17,25 17,19.882950319390353 15,25 C13,25 11,25 11,25 Z\" /></svg>", "expected_label": 5, "satisfy_requirements": true, "predicted_label": 5, "prediction_quality": 0.027672693133354187}], "seed": 88}