{"name": "ind1822", "unsafe_region": [0.765102014040541, 0.923839901827522], "archive_sparseness": 7.121579647064209, "mbr": {"svg": "<svg version=\"1.0\" xmlns=\"http://www.w3.org/2000/svg\" height=\"28\" width=\"28\"><path d=\" M11,25 C9,24 9,24 11,24 C12,24 14,24 15,21.639016443232553 C17,25 17,25 15,25 C13,25 11,25 11,25 Z\" /></svg>", "expected_label": 5, "satisfy_requirements": false, "predicted_label": 3, "prediction_quality": -0.09825386106967926}, "neighbors": [{"svg": "<svg version=\"1.0\" xmlns=\"http://www.w3.org/2000/svg\" height=\"28\" width=\"28\"><path d=\" M11,25 C9,24 9,24 11,24 C12,24 14,24 15,21.639016443232553 C17,25 17,25 15,25 C13,25 11,21.932197466388622 11,25 Z\" /></svg>", "expected_label": 5, "satisfy_requirements": false, "predicted_label": 3, "prediction_quality": -0.021638408303260803}, {"svg": "<svg version=\"1.0\" xmlns=\"http://www.w3.org/2000/svg\" height=\"28\" width=\"28\"><path d=\" M11,25 C9,24 9,24 11,24 C12,24 14,24 15,21.639016443232553 C17,25 17,25 12.835156759437861,25 C13,25 11,25 11,25 Z\" /></svg>", "expected_label": 5, "satisfy_requirements": false, "predicted_label": 3, "prediction_quality": -0.10071901977062225}, {"svg": "<svg version=\"1.0\" xmlns=\"http://www.w3.org/2000/svg\" height=\"28\" width=\"28\"><path d=\" M11,25 C9,24 9,24 11,24 C12,24 14,24 15,21.639016443232553 C17,25 17,25 15,25 C13,25 11,21.769868332955806 11,25 Z\" /></svg>", "expected_label": 5, "satisfy_requirements": false, "predicted_label": 3, "prediction_quality": -0.022973522543907166}, {"svg": "<svg version=\"1.0\" xmlns=\"http://www.w3.org/2000/svg\" height=\"28\" width=\"28\"><path d=\" M11,25 C12.291546518361182,24 9,24 11,24 C12,24 14,24 15,21.639016443232553 C17,25 17,25 15,25 C13,25 11,25 11,25 Z\" /></svg>", "expected_label": 5, "satisfy_requirements": false, "predicted_label": 3, "prediction_quality": -0.039643511176109314}, {"svg": "<svg version=\"1.0\" xmlns=\"http://www.w3.org/2000/svg\" height=\"28\" width=\"28\"><path d=\" M11,25 C9,24 9,24 11,24 C12,24 14,24 15,26.469120136062042 C17,25 17,25 15,25 C13,25 11,25 11,25 Z\" /></svg>", "expected_label": 5, "satisfy_requirements": true, "predicted_label": 5, "prediction_quality": 0.01835833489894867}, {"svg": "<svg version=\"1.0\" xmlns=\"http://www.w3.org/2000/svg\" height=\"28\" width=\"28\"><path d=\" M11,25 C9,24 9,24 11,24 C12,24 14,24 9.183828257501705,21.639016443232553 C17,25 17,25 15,25 C13,25 11,25 11,25 Z\" /></svg>", "expected_label": 5, "satisfy_requirements": true, "predicted_label": 5, "prediction_quality": 0.012651458382606506}, {"svg": "<svg version=\"1.0\" xmlns=\"http://www.w3.org/2000/svg\" height=\"28\" width=\"28\"><path d=\" M11,25 C9,24 9,24 11,24 C12,18.934917006944733 14,24 15,21.639016443232553 C17,25 17,25 15,25 C13,25 11,25 11,25 Z\" /></svg>", "expected_label": 5, "satisfy_requirements": false, "predicted_label": 3, "prediction_quality": -0.09734894335269928}, {"svg": "<svg version=\"1.0\" xmlns=\"http://www.w3.org/2000/svg\" height=\"28\" width=\"28\"><path d=\" M11,25 C9,24 9,24 11,24 C12,24 14,21.707660091498013 15,21.639016443232553 C17,25 17,25 15,25 C13,25 11,25 11,25 Z\" /></svg>", "expected_label": 5, "satisfy_requirements": false, "predicted_label": 3, "prediction_quality": -0.1336042881011963}, {"svg": "<svg version=\"1.0\" xmlns=\"http://www.w3.org/2000/svg\" height=\"28\" width=\"28\"><path d=\" M11,25 C9,24 10.825769764396288,24 11,24 C12,24 14,24 15,21.639016443232553 C17,25 17,25 15,25 C13,25 11,25 11,25 Z\" /></svg>", "expected_label": 5, "satisfy_requirements": false, "predicted_label": 3, "prediction_quality": -0.0706828236579895}, {"svg": "<svg version=\"1.0\" xmlns=\"http://www.w3.org/2000/svg\" height=\"28\" width=\"28\"><path d=\" M11,25 C9,24 9,24 11,24 C12,24 14,18.970691000446006 15,21.639016443232553 C17,25 17,25 15,25 C13,25 11,25 11,25 Z\" /></svg>", "expected_label": 5, "satisfy_requirements": false, "predicted_label": 3, "prediction_quality": -0.15587924420833588}, {"svg": "<svg version=\"1.0\" xmlns=\"http://www.w3.org/2000/svg\" height=\"28\" width=\"28\"><path d=\" M11,25 C9,24 9,24 11,24 C12,24 14,24 15,21.639016443232553 C17,25 17,25 15,25 C13,21.718005803273257 11,25 11,25 Z\" /></svg>", "expected_label": 5, "satisfy_requirements": false, "predicted_label": 1, "prediction_quality": -0.04709511995315552}, {"svg": "<svg version=\"1.0\" xmlns=\"http://www.w3.org/2000/svg\" height=\"28\" width=\"28\"><path d=\" M11,25 C13.086049084507582,24 9,24 11,24 C12,24 14,24 15,21.639016443232553 C17,25 17,25 15,25 C13,25 11,25 11,25 Z\" /></svg>", "expected_label": 5, "satisfy_requirements": false, "predicted_label": 3, "prediction_quality": -0.030873417854309082}, {"svg": "<svg version=\"1.0\" xmlns=\"http://www.w3.org/2000/svg\" height=\"28\" width=\"28\"><path d=\" M10.023045806781823,25 C9,24 9,24 11,24 C12,24 14,24 15,21.639016443232553 C17,25 17,25 15,25 C13,25 11,25 11,25 Z\" /></svg>", "expected_label": 5, "satisfy_requirements": false, "predicted_label": 3, "prediction_quality": -0.14920511841773987}, {"svg": "<svg version=\"1.0\" xmlns=\"http://www.w3.org/2000/svg\" height=\"28\" width=\"28\"><path d=\" M11,25 C9,24 10.965714839184168,24 11,24 C12,24 14,24 15,21.639016443232553 C17,25 17,25 15,25 C13,25 11,25 11,25 Z\" /></svg>", "expected_label": 5, "satisfy_requirements": false, "predicted_label": 3, "prediction_quality": -0.06937064230442047}, {"svg": "<svg version=\"1.0\" xmlns=\"http://www.w3.org/2000/svg\" height=\"28\" width=\"28\"><path d=\" M11,25 C9,24 9,24 11,24 C12,24 14,24 15,21.639016443232553 C11.499504154032028,25 17,25 15,25 C13,25 11,25 11,25 Z\" /></svg>", "expected_label": 5, "satisfy_requirements": true, "predicted_label": 5, "prediction_quality": 0.021778225898742676}, {"svg": "<svg version=\"1.0\" xmlns=\"http://www.w3.org/2000/svg\" height=\"28\" width=\"28\"><path d=\" M11,25 C9,24 9,24 11,21.90633932350945 C12,24 14,24 15,21.639016443232553 C17,25 17,25 15,25 C13,25 11,25 11,25 Z\" /></svg>", "expected_label": 5, "satisfy_requirements": false, "predicted_label": 3, "prediction_quality": -0.05924537777900696}, {"svg": "<svg version=\"1.0\" xmlns=\"http://www.w3.org/2000/svg\" height=\"28\" width=\"28\"><path d=\" M11,25 C9,24 9,24 11,24 C12,24 14,24 15,21.639016443232553 C17,25 17,25 15,25 C13,23.95831541483028 11,25 11,25 Z\" /></svg>", "expected_label": 5, "satisfy_requirements": false, "predicted_label": 3, "prediction_quality": -0.05002428591251373}, {"svg": "<svg version=\"1.0\" xmlns=\"http://www.w3.org/2000/svg\" height=\"28\" width=\"28\"><path d=\" M11,25 C9,24 9,24 11,24 C12,24 14,24 15,21.639016443232553 C17,25 17,25 13.432113353237241,25 C13,25 11,25 11,25 Z\" /></svg>", "expected_label": 5, "satisfy_requirements": false, "predicted_label": 3, "prediction_quality": -0.10033334791660309}, {"svg": "<svg version=\"1.0\" xmlns=\"http://www.w3.org/2000/svg\" height=\"28\" width=\"28\"><path d=\" M11,25 C9,24 9,24 11,24 C12,24 14,24 15,21.639016443232553 C17,25 21.825909866128967,25 15,25 C13,25 11,25 11,25 Z\" /></svg>", "expected_label": 5, "satisfy_requirements": false, "predicted_label": 3, "prediction_quality": -0.16785970330238342}, {"svg": "<svg version=\"1.0\" xmlns=\"http://www.w3.org/2000/svg\" height=\"28\" width=\"28\"><path d=\" M11,25 C9,24 9,24 11,24 C12,21.97553281913113 14,24 15,21.639016443232553 C17,25 17,25 15,25 C13,25 11,25 11,25 Z\" /></svg>", "expected_label": 5, "satisfy_requirements": false, "predicted_label": 3, "prediction_quality": -0.16647392511367798}, {"svg": "<svg version=\"1.0\" xmlns=\"http://www.w3.org/2000/svg\" height=\"28\" width=\"28\"><path d=\" M11,25 C9,24 9,24 11,24 C12,24 14,24 15,21.639016443232553 C17,25 17,25 15,25 C13,25 11,25 11,27.951263477213942 Z\" /></svg>", "expected_label": 5, "satisfy_requirements": false, "predicted_label": 3, "prediction_quality": -0.10343067348003387}, {"svg": "<svg version=\"1.0\" xmlns=\"http://www.w3.org/2000/svg\" height=\"28\" width=\"28\"><path d=\" M5.228949768481992,25 C9,24 9,24 11,24 C12,24 14,24 15,21.639016443232553 C17,25 17,25 15,25 C13,25 11,25 11,25 Z\" /></svg>", "expected_label": 5, "satisfy_requirements": false, "predicted_label": 3, "prediction_quality": -0.4282621443271637}, {"svg": "<svg version=\"1.0\" xmlns=\"http://www.w3.org/2000/svg\" height=\"28\" width=\"28\"><path d=\" M11,25 C9,24 9,24 11,24 C12,24 14,24 15,21.639016443232553 C17,25 17,25 15,25 C13,19.607156490274495 11,25 11,25 Z\" /></svg>", "expected_label": 5, "satisfy_requirements": false, "predicted_label": 1, "prediction_quality": -0.026065319776535034}, {"svg": "<svg version=\"1.0\" xmlns=\"http://www.w3.org/2000/svg\" height=\"28\" width=\"28\"><path d=\" M11,25 C9,24 9,24 11,24 C12,24 14,24 15,21.639016443232553 C17,25 17,25 18.743778505105073,25 C13,25 11,25 11,25 Z\" /></svg>", "expected_label": 5, "satisfy_requirements": false, "predicted_label": 3, "prediction_quality": -0.11523818969726562}, {"svg": "<svg version=\"1.0\" xmlns=\"http://www.w3.org/2000/svg\" height=\"28\" width=\"28\"><path d=\" M11,25 C9,24 9,24 11,24 C12,24 14,24 15,21.639016443232553 C17,25 17,25 15,25 C13,25 11,27.23455609995913 11,25 Z\" /></svg>", "expected_label": 5, "satisfy_requirements": false, "predicted_label": 3, "prediction_quality": -0.09819120168685913}, {"svg": "<svg version=\"1.0\" xmlns=\"http://www.w3.org/2000/svg\" height=\"28\" width=\"28\"><path d=\" M11,25 C9,24 9,24 11,24 C12,24 14,24 15,21.639016443232553 C17,25 17,25 20.494103154496205,25 C13,25 11,25 11,25 Z\" /></svg>", "expected_label": 5, "satisfy_requirements": false, "predicted_label": 3, "prediction_quality": -0.12483979761600494}, {"svg": "<svg version=\"1.0\" xmlns=\"http://www.w3.org/2000/svg\" height=\"28\" width=\"28\"><path d=\" M11,25 C9,24 9,24 11,24 C12,24 14,24 15,21.639016443232553 C17,25 17,25 15.261560872536009,25 C13,25 11,25 11,25 Z\" /></svg>", "expected_label": 5, "satisfy_requirements": false, "predicted_label": 3, "prediction_quality": -0.09803779423236847}, {"svg": "<svg version=\"1.0\" xmlns=\"http://www.w3.org/2000/svg\" height=\"28\" width=\"28\"><path d=\" M11,25 C9,24 9,24 11,24 C12,24 14,24 15,21.639016443232553 C17,21.484971800338617 17,25 15,25 C13,25 11,25 11,25 Z\" /></svg>", "expected_label": 5, "satisfy_requirements": false, "predicted_label": 3, "prediction_quality": -0.147763192653656}, {"svg": "<svg version=\"1.0\" xmlns=\"http://www.w3.org/2000/svg\" height=\"28\" width=\"28\"><path d=\" M11,25 C9,24 9,24 11,24 C12,24 14,24 15,21.639016443232553 C17,25 21.617184326016503,25 15,25 C13,25 11,25 11,25 Z\" /></svg>", "expected_label": 5, "satisfy_requirements": false, "predicted_label": 3, "prediction_quality": -0.1611739844083786}, {"svg": "<svg version=\"1.0\" xmlns=\"http://www.w3.org/2000/svg\" height=\"28\" width=\"28\"><path d=\" M11,25 C9,24 9,24 11,24 C12,24 14,24.113575278107117 15,21.639016443232553 C17,25 17,25 15,25 C13,25 11,25 11,25 Z\" /></svg>", "expected_label": 5, "satisfy_requirements": false, "predicted_label": 3, "prediction_quality": -0.09004926681518555}, {"svg": "<svg version=\"1.0\" xmlns=\"http://www.w3.org/2000/svg\" height=\"28\" width=\"28\"><path d=\" M11,19.147552885624076 C9,24 9,24 11,24 C12,24 14,24 15,21.639016443232553 C17,25 17,25 15,25 C13,25 11,25 11,25 Z\" /></svg>", "expected_label": 5, "satisfy_requirements": true, "predicted_label": 5, "prediction_quality": 0.048315420746803284}, {"svg": "<svg version=\"1.0\" xmlns=\"http://www.w3.org/2000/svg\" height=\"28\" width=\"28\"><path d=\" M11,25 C9,24 9,24.906879527258738 11,24 C12,24 14,24 15,21.639016443232553 C17,25 17,25 15,25 C13,25 11,25 11,25 Z\" /></svg>", "expected_label": 5, "satisfy_requirements": false, "predicted_label": 3, "prediction_quality": -0.07878808677196503}, {"svg": "<svg version=\"1.0\" xmlns=\"http://www.w3.org/2000/svg\" height=\"28\" width=\"28\"><path d=\" M11,25 C9,24 9,24 11,24 C12,24 11.96521767213087,24 15,21.639016443232553 C17,25 17,25 15,25 C13,25 11,25 11,25 Z\" /></svg>", "expected_label": 5, "satisfy_requirements": false, "predicted_label": 3, "prediction_quality": -0.13679711520671844}, {"svg": "<svg version=\"1.0\" xmlns=\"http://www.w3.org/2000/svg\" height=\"28\" width=\"28\"><path d=\" M11,25 C9,24 9,24 11,24 C12,24 14,24 15,21.639016443232553 C14.170312226584775,25 17,25 15,25 C13,25 11,25 11,25 Z\" /></svg>", "expected_label": 5, "satisfy_requirements": false, "predicted_label": 3, "prediction_quality": -0.05744077265262604}, {"svg": "<svg version=\"1.0\" xmlns=\"http://www.w3.org/2000/svg\" height=\"28\" width=\"28\"><path d=\" M11,21.770291475901658 C9,24 9,24 11,24 C12,24 14,24 15,21.639016443232553 C17,25 17,25 15,25 C13,25 11,25 11,25 Z\" /></svg>", "expected_label": 5, "satisfy_requirements": true, "predicted_label": 5, "prediction_quality": 0.015497192740440369}, {"svg": "<svg version=\"1.0\" xmlns=\"http://www.w3.org/2000/svg\" height=\"28\" width=\"28\"><path d=\" M11,25 C9,24 9,24 11,24 C12,24 14,24 15,21.639016443232553 C17,25 19.845789119356425,25 15,25 C13,25 11,25 11,25 Z\" /></svg>", "expected_label": 5, "satisfy_requirements": false, "predicted_label": 3, "prediction_quality": -0.128422349691391}, {"svg": "<svg version=\"1.0\" xmlns=\"http://www.w3.org/2000/svg\" height=\"28\" width=\"28\"><path d=\" M11,25 C9,24 8.525618310973682,24 11,24 C12,24 14,24 15,21.639016443232553 C17,25 17,25 15,25 C13,25 11,25 11,25 Z\" /></svg>", "expected_label": 5, "satisfy_requirements": false, "predicted_label": 3, "prediction_quality": -0.10102401673793793}, {"svg": "<svg version=\"1.0\" xmlns=\"http://www.w3.org/2000/svg\" height=\"28\" width=\"28\"><path d=\" M11,25 C9,24 9,24 11,24 C12,24 14,24 15,21.639016443232553 C17,25 17,25 15,21.537883645597013 C13,25 11,25 11,25 Z\" /></svg>", "expected_label": 5, "satisfy_requirements": true, "predicted_label": 5, "prediction_quality": 0.01599501073360443}, {"svg": "<svg version=\"1.0\" xmlns=\"http://www.w3.org/2000/svg\" height=\"28\" width=\"28\"><path d=\" M11,25 C9,24 9,24 11,24 C12,24 14,24 15.123011601909736,21.639016443232553 C17,25 17,25 15,25 C13,25 11,25 11,25 Z\" /></svg>", "expected_label": 5, "satisfy_requirements": false, "predicted_label": 3, "prediction_quality": -0.10301390290260315}, {"svg": "<svg version=\"1.0\" xmlns=\"http://www.w3.org/2000/svg\" height=\"28\" width=\"28\"><path d=\" M11,25 C9,24 9,24 11,24 C12,24 14,24 15,21.639016443232553 C17,25 17,25 15,27.131788917174188 C13,25 11,25 11,25 Z\" /></svg>", "expected_label": 5, "satisfy_requirements": true, "predicted_label": 5, "prediction_quality": 0.004580497741699219}, {"svg": "<svg version=\"1.0\" xmlns=\"http://www.w3.org/2000/svg\" height=\"28\" width=\"28\"><path d=\" M11,25 C9,24 9,24 11,24 C12,24 14,24 17.369168200111552,21.639016443232553 C17,25 17,25 15,25 C13,25 11,25 11,25 Z\" /></svg>", "expected_label": 5, "satisfy_requirements": false, "predicted_label": 3, "prediction_quality": -0.07789677381515503}, {"svg": "<svg version=\"1.0\" xmlns=\"http://www.w3.org/2000/svg\" height=\"28\" width=\"28\"><path d=\" M11,25 C7.228363451533853,24 9,24 11,24 C12,24 14,24 15,21.639016443232553 C17,25 17,25 15,25 C13,25 11,25 11,25 Z\" /></svg>", "expected_label": 5, "satisfy_requirements": false, "predicted_label": 3, "prediction_quality": -0.14010687172412872}, {"svg": "<svg version=\"1.0\" xmlns=\"http://www.w3.org/2000/svg\" height=\"28\" width=\"28\"><path d=\" M11,25 C9,24 9,24 11,24 C12,24 14,18.408346583616904 15,21.639016443232553 C17,25 17,25 15,25 C13,25 11,25 11,25 Z\" /></svg>", "expected_label": 5, "satisfy_requirements": false, "predicted_label": 3, "prediction_quality": -0.15274657309055328}, {"svg": "<svg version=\"1.0\" xmlns=\"http://www.w3.org/2000/svg\" height=\"28\" width=\"28\"><path d=\" M11,25 C9,19.005279483411528 9,24 11,24 C12,24 14,24 15,21.639016443232553 C17,25 17,25 15,25 C13,25 11,25 11,25 Z\" /></svg>", "expected_label": 5, "satisfy_requirements": false, "predicted_label": 3, "prediction_quality": -0.012702524662017822}, {"svg": "<svg version=\"1.0\" xmlns=\"http://www.w3.org/2000/svg\" height=\"28\" width=\"28\"><path d=\" M12.93974943861149,25 C9,24 9,24 11,24 C12,24 14,24 15,21.639016443232553 C17,25 17,25 15,25 C13,25 11,25 11,25 Z\" /></svg>", "expected_label": 5, "satisfy_requirements": false, "predicted_label": 3, "prediction_quality": -0.03149384260177612}, {"svg": "<svg version=\"1.0\" xmlns=\"http://www.w3.org/2000/svg\" height=\"28\" width=\"28\"><path d=\" M11,25 C9,24 9,24 11,24 C12,24 14,20.414928781073076 15,21.639016443232553 C17,25 17,25 15,25 C13,25 11,25 11,25 Z\" /></svg>", "expected_label": 5, "satisfy_requirements": false, "predicted_label": 3, "prediction_quality": -0.14277531206607819}, {"svg": "<svg version=\"1.0\" xmlns=\"http://www.w3.org/2000/svg\" height=\"28\" width=\"28\"><path d=\" M11,25 C9,24 9,24 11,24 C12,18.7220347755171 14,24 15,21.639016443232553 C17,25 17,25 15,25 C13,25 11,25 11,25 Z\" /></svg>", "expected_label": 5, "satisfy_requirements": false, "predicted_label": 3, "prediction_quality": -0.09151676297187805}, {"svg": "<svg version=\"1.0\" xmlns=\"http://www.w3.org/2000/svg\" height=\"28\" width=\"28\"><path d=\" M11,25 C9,24 9,24 11,25.95474457918582 C12,24 14,24 15,21.639016443232553 C17,25 17,25 15,25 C13,25 11,25 11,25 Z\" /></svg>", "expected_label": 5, "satisfy_requirements": false, "predicted_label": 3, "prediction_quality": -0.014290764927864075}, {"svg": "<svg version=\"1.0\" xmlns=\"http://www.w3.org/2000/svg\" height=\"28\" width=\"28\"><path d=\" M11,27.570799379099142 C9,24 9,24 11,24 C12,24 14,24 15,21.639016443232553 C17,25 17,25 15,25 C13,25 11,25 11,25 Z\" /></svg>", "expected_label": 5, "satisfy_requirements": false, "predicted_label": 3, "prediction_quality": -0.19008296728134155}, {"svg": "<svg version=\"1.0\" xmlns=\"http://www.w3.org/2000/svg\" height=\"28\" width=\"28\"><path d=\" M11,25 C9,24 9,24 11,24 C12,24 14,24 15,21.639016443232553 C17,25 17,25 15,25 C13,25 11,19.294288520771918 11,25 Z\" /></svg>", "expected_label": 5, "satisfy_requirements": false, "predicted_label": 3, "prediction_quality": -0.051707953214645386}], "seed": 87}